README.md
setup.cfg
setup.py
cloudgenix_idname/__init__.py
cloudgenix_idname.egg-info/PKG-INFO
cloudgenix_idname.egg-info/SOURCES.txt
cloudgenix_idname.egg-info/dependency_links.txt
cloudgenix_idname.egg-info/requires.txt
cloudgenix_idname.egg-info/top_level.txt