Metadata-Version: 1.1
Name: cloudgenix-idname
Version: 1.1.3
Summary: ID -> Name translator for the CloudGenix Python SDK
Home-page: https://github.com/ebob9/cloudgenix-idname
Author: Aaron Edwards
Author-email: cloudgenix_idname@ebob9.com
License: MIT
Platform: UNKNOWN
Classifier: Development Status :: 5 - Production/Stable
Classifier: Intended Audience :: Developers
Classifier: License :: OSI Approved :: MIT License
Classifier: Programming Language :: Python :: 2.7
Classifier: Programming Language :: Python :: 3
